alphashape/__init__.py
alphashape/_version.py
alphashape/alphashape.py
alphashape/cli.py
alphashape/optimizealpha.py
alphashape-1.3.1.dist-info/AUTHORS.rst
alphashape-1.3.1.dist-info/LICENSE
alphashape-1.3.1.dist-info/METADATA
alphashape-1.3.1.dist-info/WHEEL
alphashape-1.3.1.dist-info/entry_points.txt
alphashape-1.3.1.dist-info/top_level.txt
alphashape-1.3.1.dist-info/RECORD
