Metadata-Version: 2.1
Name: alphashape
Version: 1.3.1
Summary: Toolbox for generating alpha shapes.
Home-page: https://github.com/bellockk/alphashape
Author: Kenneth E. Bellock
Author-email: ken@bellock.net
License: MIT license
Keywords: alphashape
Platform: UNKNOWN
Classifier: Development Status :: 5 - Production/Stable
Classifier: Intended Audience :: Science/Research
Classifier: Operating System :: OS Independent
Classifier: Topic :: Scientific/Engineering
Classifier: License :: OSI Approved :: MIT License
Classifier: Natural Language :: English
Classifier: Programming Language :: Python :: 3
Classifier: Programming Language :: Python :: 3.6
Classifier: Programming Language :: Python :: 3.7
Classifier: Programming Language :: Python :: 3.8
Classifier: Programming Language :: Python :: 3.9
